guigaga/__about__.py
guigaga/__init__.py
guigaga/decorator.py
guigaga/guigaga.py
guigaga/introspect.py
guigaga/logger.py
guigaga/types.py
guigaga-0.0.10.dist-info/METADATA
guigaga-0.0.10.dist-info/WHEEL
guigaga-0.0.10.dist-info/licenses/LICENSE.txt
guigaga-0.0.10.dist-info/RECORD
